.source hello.jasm
.class public EscapeSequences

.method public static main ([Ljava/lang/String;)V
.code
    getstatic java/lang/System out Ljava/io/PrintStream;
    dup
    dup
    dup
    dup
    dup
    ldc "Newline: [\n]"
    invokevirtual java/io/PrintStream println (Ljava/lang/String;)V
    ldc "Tab: [\t]"
    invokevirtual java/io/PrintStream println (Ljava/lang/String;)V
    ldc "Backspace: [\b]"
    invokevirtual java/io/PrintStream println (Ljava/lang/String;)V
    ldc "Double quote: [\"]"
    invokevirtual java/io/PrintStream println (Ljava/lang/String;)V
    ldc "Single quote: [\']"
    invokevirtual java/io/PrintStream println (Ljava/lang/String;)V
    ldc "Backslash: [\\]"
    invokevirtual java/io/PrintStream println (Ljava/lang/String;)V

    # the next two lines should fail if uncommented:
    #ldc "Invalid: [\u2f3a]"
    #ldc "Invalid: [\m]"

    getstatic java/lang/System out Ljava/io/PrintStream;
    dup
    dup
    dup
    dup
    dup
    dup
    dup
    dup
    bipush '\0'
    invokevirtual java/io/PrintStream println (I)V
    bipush '\n'
    invokevirtual java/io/PrintStream println (I)V
    bipush '\t'
    invokevirtual java/io/PrintStream println (I)V
    bipush '\b'
    invokevirtual java/io/PrintStream println (I)V
    bipush '\"'
    invokevirtual java/io/PrintStream println (I)V
    bipush '\''
    invokevirtual java/io/PrintStream println (I)V
    bipush '\\'
    invokevirtual java/io/PrintStream println (I)V
    bipush '"'
    invokevirtual java/io/PrintStream println (I)V
    bipush 'A'
    invokevirtual java/io/PrintStream println (I)V

    return
.end code
